[{"siteName":"Lakeside","address":"1 Lakeshore Dr, Cosham, Portsmouth PO6 3EN, UK","lon":-1.081932,"driveTime":"19 mins"},{"siteName":"Poole Test","address":"1 Boyd Rd, Poole , UK","lon":-1.921772,"driveTime":"59 mins"},{"siteName":"Poole Test","address":"1 Boyd Rd, Poole , UK","lon":-1.921772,"driveTime":"59 mins"},{"siteName":"Lorna Doone","address":"Fair Winds, W End Rd, Bursledon, Southampton, UK","lon":-1.318583,"driveTime":"11 mins"},{"siteName":"Lorna Doone 1","address":"Fair Winds, W End Rd, Bursledon, Southampton, UK","lon":-1.317906,"driveTime":"11 mins"},{"siteName":"Victory Close","address":"8 Victory Cl, Chandler's Ford, Eastleigh, UK","lon":-1.392525,"driveTime":"23 mins"},{"siteName":"Tester now ","address":"112 Chalvington Rd, Chandler's Ford, Eastleigh, UK","lon":-1.383447,"driveTime":"20 mins"},{"siteName":"Bournemouth Co-op","address":"5 Madeira Rd, Bournemouth, UK","lon":-1.868084,"driveTime":"51 mins"},{"siteName":"Let’s see","address":"White Cottage, Dorking Rd, Warnham, Horsham, UK","lon":-0.336589,"driveTime":"1 hour 19 mins"}]