[
  {
    "Branch Code": 649,
    "Store Name": "The Co-operative Funeralcare - Bedhampton",
    "Monday Opening Hours": "10:00 - 16:00",
    "Tuesday Opening Hours": "10:00 - 16:00",
    "Wednesday Opening Hours": "10:00 - 16:00",
    "Thursday Opening Hours": "10:00 - 16:00",
    "Friday Opening Hours": "10:00 - 16:00",
    "Area": 1,
    "Area Client Experience Manager": "Tracie Sharp",
    "Area Client Experience Manager Phone Number": 7885843887,
    "Street": "96 Bedhampton Road,",
    "Address 1": "Bedhampton",
    "Town": "Havant, ",
    "Postcode": "PO9 3EZ",
    "Telephone": "02392 453549",
    "Email": "bedhamptonfuneral@southerncoops.co.uk",
    "Latitude": 50.8553519,
    "Longitude": -1.0007596,
    "Car Park": "",
    "SharePoint": "https://mostlane.sharepoint.com/Mostlane%20Shared%20Documents/Forms/AllItems.aspx?id=%2FMostlane%20Shared%20Documents%2FMostlane%20Construction%2FTSC%20Compliance%2FELS%2F649%20Bedhampton",
    "5_Year": "06/12/2026",
    "PAT": "17/01/2026",
    "EM": "17/01/2026",
    "PV": "",
    "EV": "",
    "PUMP": ""
  },
  {
    "Branch Code": 712,
    "Store Name": "The Co-operative Funeralcare - Bishops Waltham",
    "Monday Opening Hours": "10:00 - 16:00",
    "Tuesday Opening Hours": "10:00 - 16:00",
    "Wednesday Opening Hours": "10:00 - 16:00",
    "Thursday Opening Hours": "10:00 - 16:00",
    "Friday Opening Hours": "10:00 - 16:00",
    "Area": 1,
    "Area Client Experience Manager": "Tracie Sharp",
    "Area Client Experience Manager Phone Number": 7885843887,
    "Street": "24 High Street",
    "Address 1": "St George's Square",
    "Town": "Bishops Waltham",
    "Postcode": "SO32 1AA",
    "Telephone": "01489 896305",
    "Email": "BishopsWalthamFuneral@southerncoops.co.uk",
    "Latitude": 50.9536373,
    "Longitude": -1.2130043,
    "Car Park": "No",
    "SharePoint": "https://mostlane.sharepoint.com/Mostlane%20Shared%20Documents/Forms/AllItems.aspx?id=%2FMostlane%20Shared%20Documents%2FMostlane%20Construction%2FTSC%20Compliance%2FELS%2F712%20Bishops Waltham",
    "5_Year": "10/06/2030",
    "PAT": "31/01/2026",
    "EM": "31/01/2026",
    "PV": "",
    "EV": "",
    "PUMP": ""
  },
  {
    "Branch Code": 646,
    "Store Name": "The Co-operative Funeralcare - Copnor",
    "Monday Opening Hours": "10:00 - 16:00",
    "Tuesday Opening Hours": "10:00 - 16:00",
    "Wednesday Opening Hours": "10:00 - 16:00",
    "Thursday Opening Hours": "10:00 - 16:00",
    "Friday Opening Hours": "10:00 - 16:00",
    "Area": 1,
    "Area Client Experience Manager": "Tracie Sharp",
    "Area Client Experience Manager Phone Number": 7885843887,
    "Street": "65 Tangier Road",
    "Address 1": "Copnor",
    "Town": "Portsmouth",
    "Postcode": "PO3 6JH",
    "Telephone": "02392 698362",
    "Email": "copnorfuneral@southerncoops.co.uk",
    "Latitude": 50.8088283,
    "Longitude": -1.060558,
    "Car Park": "No",
    "SharePoint": "https://mostlane.sharepoint.com/Mostlane%20Shared%20Documents/Forms/AllItems.aspx?id=%2FMostlane%20Shared%20Documents%2FMostlane%20Construction%2FTSC%20Compliance%2FELS%2F646%20Copnor",
    "5_Year": "25/11/2026",
    "PAT": "03/01/2026",
    "EM": "03/01/2026",
    "PV": "",
    "EV": "",
    "PUMP": ""
  },
  {
    "Branch Code": 624,
    "Store Name": "The Co-operative Funeralcare - Cosham",
    "Monday Opening Hours": "10:00 - 16:00",
    "Tuesday Opening Hours": "10:00 - 16:00",
    "Wednesday Opening Hours": "10:00 - 16:00",
    "Thursday Opening Hours": "10:00 - 16:00",
    "Friday Opening Hours": "10:00 - 16:00",
    "Area": 1,
    "Area Client Experience Manager": "Tracie Sharp",
    "Area Client Experience Manager Phone Number": 7885843887,
    "Street": "47 High Street",
    "Address 1": "",
    "Town": "Cosham",
    "Postcode": "PO6 3AX",
    "Telephone": "02392 383460",
    "Email": "coshamfuneral@southerncoops.co.uk",
    "Latitude": 50.8450482,
    "Longitude": -1.0668034,
    "Car Park": "No",
    "SharePoint": "https://mostlane.sharepoint.com/Mostlane%20Shared%20Documents/Forms/AllItems.aspx?id=%2FMostlane%20Shared%20Documents%2FMostlane%20Construction%2FTSC%20Compliance%2FELS%2F624%20Cosham",
    "5_Year": "25/11/2026",
    "PAT": "02/01/2026",
    "EM": "02/01/2026",
    "PV": "",
    "EV": "",
    "PUMP": ""
  },
  {
    "Branch Code": 678,
    "Store Name": "The Co-operative Funeralcare - Cowplain",
    "Monday Opening Hours": "10:00 - 16:00",
    "Tuesday Opening Hours": "10:00 - 16:00",
    "Wednesday Opening Hours": "10:00 - 16:00",
    "Thursday Opening Hours": "10:00 - 16:00",
    "Friday Opening Hours": "10:00 - 16:00",
    "Area": 1,
    "Area Client Experience Manager": "Tracie Sharp",
    "Area Client Experience Manager Phone Number": 7885843887,
    "Street": "37A London Road",
    "Address 1": "Cowplain",
    "Town": "Waterlooville",
    "Postcode": "PO8 8DF",
    "Telephone": "02392 254490",
    "Email": "cowplainfuneral@southerncoops.co.uk",
    "Latitude": 50.8934035,
    "Longitude": -1.0195236,
    "Car Park": "Yes",
    "SharePoint": "https://mostlane.sharepoint.com/Mostlane%20Shared%20Documents/Forms/AllItems.aspx?id=%2FMostlane%20Shared%20Documents%2FMostlane%20Construction%2FTSC%20Compliance%2FELS%2F678%20Cowplain",
    "5_Year": "06/12/2026",
    "PAT": "09/01/2026",
    "EM": "09/01/2026",
    "PV": "",
    "EV": "",
    "PUMP": ""
  },
  {
    "Branch Code": 676,
    "Store Name": "The Co-operative Funeralcare - Eastney",
    "Monday Opening Hours": "10:00 - 16:00",
    "Tuesday Opening Hours": "10:00 - 16:00",
    "Wednesday Opening Hours": "10:00 - 16:00",
    "Thursday Opening Hours": "10:00 - 16:00",
    "Friday Opening Hours": "10:00 - 16:00",
    "Area": 1,
    "Area Client Experience Manager": "Tracie Sharp",
    "Area Client Experience Manager Phone Number": 7885843887,
    "Street": "131 Eastney Road",
    "Address 1": "Eastney",
    "Town": "Portsmouth",
    "Postcode": "PO4 8DZ",
    "Telephone": "02392 873218",
    "Email": "EastneyFuneral@southerncoops.co.uk",
    "Latitude": 50.7899219,
    "Longitude": -1.055309,
    "Car Park": "No",
    "SharePoint": "https://mostlane.sharepoint.com/Mostlane%20Shared%20Documents/Forms/AllItems.aspx?id=%2FMostlane%20Shared%20Documents%2FMostlane%20Construction%2FTSC%20Compliance%2FELS%2F676%20Eastney",
    "5_Year": "08/10/2026",
    "PAT": "07/01/2026",
    "EM": "07/01/2026",
    "PV": "",
    "EV": "",
    "PUMP": ""
  },
  {
    "Branch Code": 677,
    "Store Name": "The Co-operative Funeralcare - Emsworth",
    "Monday Opening Hours": "10:00 - 16:00",
    "Tuesday Opening Hours": "10:00 - 16:00",
    "Wednesday Opening Hours": "10:00 - 16:00",
    "Thursday Opening Hours": "10:00 - 16:00",
    "Friday Opening Hours": "10:00 - 16:00",
    "Area": 1,
    "Area Client Experience Manager": "Tracie Sharp",
    "Area Client Experience Manager Phone Number": 7885843887,
    "Street": "31 North Street",
    "Address 1": "",
    "Town": "Emsworth",
    "Postcode": "PO10 7DA",
    "Telephone": "01243 376458",
    "Email": "EmsworthFuneral@southerncoops.co.uk",
    "Latitude": 50.8491542,
    "Longitude": -0.93749,
    "Car Park": "No",
    "SharePoint": "https://mostlane.sharepoint.com/Mostlane%20Shared%20Documents/Forms/AllItems.aspx?id=%2FMostlane%20Shared%20Documents%2FMostlane%20Construction%2FTSC%20Compliance%2FELS%2F677%20Emsworth",
    "5_Year": "09/08/2026",
    "PAT": "08/01/2026",
    "EM": "08/01/2026",
    "PV": "",
    "EV": "",
    "PUMP": ""
  },
  {
    "Branch Code": 651,
    "Store Name": "The Co-operative Funeralcare - Fratton",
    "Monday Opening Hours": "09:00 - 17:00",
    "Tuesday Opening Hours": "09:00 - 17:00",
    "Wednesday Opening Hours": "09:00 - 17:00",
    "Thursday Opening Hours": "09:00 - 17:00",
    "Friday Opening Hours": "09:00 - 17:00",
    "Area": 1,
    "Area Client Experience Manager": "Tracie Sharp",
    "Area Client Experience Manager Phone Number": 7885843887,
    "Street": "157 Fratton Road",
    "Address 1": "Fratton",
    "Town": "Portsmouth",
    "Postcode": "PO1 5ER",
    "Telephone": "02392 863031",
    "Email": "FrattonFuneral@southerncoops.co.uk",
    "Latitude": 50.8006579,
    "Longitude": -1.0774215,
    "Car Park": "Yes",
    "SharePoint": "https://mostlane.sharepoint.com/Mostlane%20Shared%20Documents/Forms/AllItems.aspx?id=%2FMostlane%20Shared%20Documents%2FMostlane%20Construction%2FTSC%20Compliance%2FELS%2F651%20Fratton",
    "5_Year": "16/12/2026",
    "PAT": "03/01/2026",
    "EM": "03/01/2026",
    "PV": "28/10/2025",
    "EV": "22/06/2025",
    "PUMP": ""
  },
  {
    "Branch Code": 673,
    "Store Name": "The Co-operative Funeralcare - Hayling Island",
    "Monday Opening Hours": "10:00 - 16:00",
    "Tuesday Opening Hours": "10:00 - 16:00",
    "Wednesday Opening Hours": "10:00 - 16:00",
    "Thursday Opening Hours": "10:00 - 16:00",
    "Friday Opening Hours": "10:00 - 16:00",
    "Area": 1,
    "Area Client Experience Manager": "Tracie Sharp",
    "Area Client Experience Manager Phone Number": 7885843887,
    "Street": "20 Mengham Road",
    "Address 1": "",
    "Town": "Hayling Island",
    "Postcode": "PO11 9BL",
    "Telephone": "02392 460047",
    "Email": "HaylingislandFuneral@southerncoops.co.uk",
    "Latitude": 50.7875207,
    "Longitude": -0.9760613,
    "Car Park": "Yes",
    "SharePoint": "https://mostlane.sharepoint.com/Mostlane%20Shared%20Documents/Forms/AllItems.aspx?id=%2FMostlane%20Shared%20Documents%2FMostlane%20Construction%2FTSC%20Compliance%2FELS%2F673%20Hayling Island",
    "5_Year": "23/04/2029",
    "PAT": "08/01/2026",
    "EM": "08/01/2026",
    "PV": "",
    "EV": "",
    "PUMP": ""
  },
  {
    "Branch Code": 653,
    "Store Name": "The Co-operative Funeralcare - Leigh Park",
    "Monday Opening Hours": "09:00 - 17:00",
    "Tuesday Opening Hours": "09:00 - 17:00",
    "Wednesday Opening Hours": "09:00 - 17:00",
    "Thursday Opening Hours": "09:00 - 17:00",
    "Friday Opening Hours": "09:00 - 17:00",
    "Area": 1,
    "Area Client Experience Manager": "Tracie Sharp",
    "Area Client Experience Manager Phone Number": 7885843887,
    "Street": "194-196 Dunsbury Way",
    "Address 1": "Leigh Park",
    "Town": "Havant",
    "Postcode": "PO9 5BQ",
    "Telephone": "02392 484499",
    "Email": "LeighparkFuneral@southerncoops.co.uk",
    "Latitude": 50.8689886,
    "Longitude": -0.9879687,
    "Car Park": "Yes",
    "SharePoint": "https://mostlane.sharepoint.com/Mostlane%20Shared%20Documents/Forms/AllItems.aspx?id=%2FMostlane%20Shared%20Documents%2FMostlane%20Construction%2FTSC%20Compliance%2FELS%2F653%20Leigh Park",
    "5_Year": "09/11/2026",
    "PAT": "17/09/2026",
    "EM": "17/09/2026",
    "PV": "",
    "EV": "",
    "PUMP": ""
  },
  {
    "Branch Code": 679,
    "Store Name": "The Co-operative Funeralcare - North End",
    "Monday Opening Hours": "10:00 - 16:00",
    "Tuesday Opening Hours": "10:00 - 16:00",
    "Wednesday Opening Hours": "10:00 - 16:00",
    "Thursday Opening Hours": "10:00 - 16:00",
    "Friday Opening Hours": "10:00 - 16:00",
    "Area": 1,
    "Area Client Experience Manager": "Tracie Sharp",
    "Area Client Experience Manager Phone Number": 7885843887,
    "Street": "52 London Road,   ",
    "Address 1": "",
    "Town": "Portsmouth,",
    "Postcode": "PO2 OLN",
    "Telephone": "02392 662534",
    "Email": "NorthendFuneral@southerncoops.co.uk",
    "Latitude": 50.8146594,
    "Longitude": -1.079598,
    "Car Park": "",
    "SharePoint": "https://mostlane.sharepoint.com/Mostlane%20Shared%20Documents/Forms/AllItems.aspx?id=%2FMostlane%20Shared%20Documents%2FMostlane%20Construction%2FTSC%20Compliance%2FELS%2F679%20North End",
    "5_Year": "30/11/2026",
    "PAT": "07/01/2026",
    "EM": "07/01/2026",
    "PV": "",
    "EV": "",
    "PUMP": ""
  },
  {
    "Branch Code": 655,
    "Store Name": "The Co-operative Funeralcare - Paulsgrove",
    "Monday Opening Hours": "10:00 - 16:00",
    "Tuesday Opening Hours": "10:00 - 16:00",
    "Wednesday Opening Hours": "10:00 - 16:00",
    "Thursday Opening Hours": "10:00 - 16:00",
    "Friday Opening Hours": "10:00 - 16:00",
    "Area": 1,
    "Area Client Experience Manager": "Tracie Sharp",
    "Area Client Experience Manager Phone Number": 7885843887,
    "Street": "181, Allaway Avenue",
    "Address 1": "Paulsgrove",
    "Town": "Portsmouth",
    "Postcode": "PO6 4HG",
    "Telephone": "02392 372106",
    "Email": "PaulsgroveFuneral@southerncoops.co.uk",
    "Latitude": 50.8497831,
    "Longitude": -1.0942391,
    "Car Park": "No",
    "SharePoint": "https://mostlane.sharepoint.com/Mostlane%20Shared%20Documents/Forms/AllItems.aspx?id=%2FMostlane%20Shared%20Documents%2FMostlane%20Construction%2FTSC%20Compliance%2FELS%2F655%20Paulsgrove",
    "5_Year": "03/12/2026",
    "PAT": "29/01/2026",
    "EM": "29/01/2026",
    "PV": "",
    "EV": "",
    "PUMP": ""
  },
  {
    "Branch Code": 658,
    "Store Name": "The Co-operative Funeralcare - Waterlooville",
    "Monday Opening Hours": "09:00 - 17:00",
    "Tuesday Opening Hours": "09:00 - 17:00",
    "Wednesday Opening Hours": "09:00 - 17:00",
    "Thursday Opening Hours": "09:00 - 17:00",
    "Friday Opening Hours": "09:00 - 17:00",
    "Area": 1,
    "Area Client Experience Manager": "Tracie Sharp",
    "Area Client Experience Manager Phone Number": 7885843887,
    "Street": "320 London Road",
    "Address 1": "",
    "Town": "Waterlooville",
    "Postcode": "PO7 7DU",
    "Telephone": "02392 266105",
    "Email": "WaterloovilleFuneral@southerncoops.co.uk",
    "Latitude": 50.8807878,
    "Longitude": -1.0300537,
    "Car Park": "Yes",
    "SharePoint": "https://mostlane.sharepoint.com/Mostlane%20Shared%20Documents/Forms/AllItems.aspx?id=%2FMostlane%20Shared%20Documents%2FMostlane%20Construction%2FTSC%20Compliance%2FELS%2F658%20Waterlooville",
    "5_Year": "10/06/2030",
    "PAT": "09/01/2026",
    "EM": "09/01/2026",
    "PV": "",
    "EV": "",
    "PUMP": ""
  },
  {
    "Branch Code": 713,
    "Store Name": "The Co-operative Funeralcare - Widley",
    "Monday Opening Hours": "10:00 - 16:00",
    "Tuesday Opening Hours": "10:00 - 16:00",
    "Wednesday Opening Hours": "10:00 - 16:00",
    "Thursday Opening Hours": "10:00 - 16:00",
    "Friday Opening Hours": "10:00 - 16:00",
    "Area": 1,
    "Area Client Experience Manager": "Tracie Sharp",
    "Area Client Experience Manager Phone Number": 7885843887,
    "Street": "1 Cornwall Buildings",
    "Address 1": "London Road",
    "Town": "Waterlooville",
    "Postcode": "PO7 5AB",
    "Telephone": "02392 378472",
    "Email": "widleyfuneral@southerncoops.co.uk",
    "Latitude": 50.8599342,
    "Longitude": -1.0480675,
    "Car Park": "Yes",
    "SharePoint": "https://mostlane.sharepoint.com/Mostlane%20Shared%20Documents/Forms/AllItems.aspx?id=%2FMostlane%20Shared%20Documents%2FMostlane%20Construction%2FTSC%20Compliance%2FELS%2F713%20Widley",
    "5_Year": "19/08/2027",
    "PAT": "19/02/2026",
    "EM": "19/02/2026",
    "PV": "",
    "EV": "",
    "PUMP": ""
  },
  {
    "Branch Code": 661,
    "Store Name": "The Co-operative Funeralcare - Bognor Regis - North Bersted",
    "Monday Opening Hours": "10:00 - 16:00",
    "Tuesday Opening Hours": "10:00 - 16:00",
    "Wednesday Opening Hours": "10:00 - 16:00",
    "Thursday Opening Hours": "10:00 - 16:00",
    "Friday Opening Hours": "10:00 - 16:00",
    "Area": 2,
    "Area Client Experience Manager": "Stefan Field",
    "Area Client Experience Manager Phone Number": 7706342321,
    "Street": "230 Chichester Road",
    "Address 1": "North Bersted",
    "Town": "Bognor Regis",
    "Postcode": "PO21 5BA",
    "Telephone": "01243 865119",
    "Email": "BognorFuneral@southerncoops.co.uk",
    "Latitude": 50.7971157,
    "Longitude": -0.6903406,
    "Car Park": "Yes",
    "SharePoint": "https://mostlane.sharepoint.com/Mostlane%20Shared%20Documents/Forms/AllItems.aspx?id=%2FMostlane%20Shared%20Documents%2FMostlane%20Construction%2FTSC%20Compliance%2FELS%2F661%20North Bersted",
    "5_Year": "03/06/2026",
    "PAT": "10/01/2026",
    "EM": "10/01/2026",
    "PV": "",
    "EV": "",
    "PUMP": ""
  },
  {
    "Branch Code": 660,
    "Store Name": "The Co-operative Funeralcare - Chichester",
    "Monday Opening Hours": "10:00 - 16:00",
    "Tuesday Opening Hours": "10:00 - 16:00",
    "Wednesday Opening Hours": "10:00 - 16:00",
    "Thursday Opening Hours": "10:00 - 16:00",
    "Friday Opening Hours": "10:00 - 16:00",
    "Area": 2,
    "Area Client Experience Manager": "Stefan Field",
    "Area Client Experience Manager Phone Number": 7706342321,
    "Street": "1 Kingsham Avenue",
    "Address 1": "",
    "Town": "Chichester",
    "Postcode": "PO19 8AW",
    "Telephone": "01243 782209",
    "Email": "ChichesterFuneral@southerncoops.co.uk",
    "Latitude": 50.8313585,
    "Longitude": -0.7726575,
    "Car Park": "No",
    "SharePoint": "https://mostlane.sharepoint.com/Mostlane%20Shared%20Documents/Forms/AllItems.aspx?id=%2FMostlane%20Shared%20Documents%2FMostlane%20Construction%2FTSC%20Compliance%2FELS%2F660%20Chichester",
    "5_Year": "06/12/2026",
    "PAT": "16/01/2026",
    "EM": "16/01/2026",
    "PV": "",
    "EV": "",
    "PUMP": ""
  },
  {
    "Branch Code": 643,
    "Store Name": "The Co-operative Funeralcare - Felpham",
    "Monday Opening Hours": "10:00 - 16:00",
    "Tuesday Opening Hours": "10:00 - 16:00",
    "Wednesday Opening Hours": "10:00 - 16:00",
    "Thursday Opening Hours": "10:00 - 16:00",
    "Friday Opening Hours": "10:00 - 16:00",
    "Area": 2,
    "Area Client Experience Manager": "Stefan Field",
    "Area Client Experience Manager Phone Number": 7706342321,
    "Street": "103 -105 Felpham Way",
    "Address 1": "",
    "Town": "Felpham",
    "Postcode": "PO22 8QB",
    "Telephone": "01243 587067",
    "Email": "FelphamFuneral@southerncoops.co.uk",
    "Latitude": 50.7936298,
    "Longitude": -0.6419225,
    "Car Park": "No",
    "SharePoint": "https://mostlane.sharepoint.com/Mostlane%20Shared%20Documents/Forms/AllItems.aspx?id=%2FMostlane%20Shared%20Documents%2FMostlane%20Construction%2FTSC%20Compliance%2FELS%2F643%20Felpham",
    "5_Year": "16/08/2027",
    "PAT": "10/01/2026",
    "EM": "10/01/2026",
    "PV": "",
    "EV": "",
    "PUMP": ""
  },
  {
    "Branch Code": 641,
    "Store Name": "The Co-operative Funeralcare - Findon Valley",
    "Monday Opening Hours": "10:00 - 16:00",
    "Tuesday Opening Hours": "10:00 - 16:00",
    "Wednesday Opening Hours": "10:00 - 16:00",
    "Thursday Opening Hours": "10:00 - 16:00",
    "Friday Opening Hours": "10:00 - 16:00",
    "Area": 2,
    "Area Client Experience Manager": "Stefan Field",
    "Area Client Experience Manager Phone Number": 7706342321,
    "Street": "202 Kings Parade",
    "Address 1": "Findon Road",
    "Town": "Worthing",
    "Postcode": "BN14 0EJ",
    "Telephone": "01903 877035",
    "Email": "Findonfuneral@southerncoops.co.uk",
    "Latitude": 50.8490413,
    "Longitude": -0.3977719,
    "Car Park": "No",
    "SharePoint": "https://mostlane.sharepoint.com/Mostlane%20Shared%20Documents/Forms/AllItems.aspx?id=%2FMostlane%20Shared%20Documents%2FMostlane%20Construction%2FTSC%20Compliance%2FELS%2F641%20Findon Valley",
    "5_Year": "17/12/2026",
    "PAT": "15/01/2026",
    "EM": "15/01/2026",
    "PV": "",
    "EV": "",
    "PUMP": ""
  },
  {
    "Branch Code": 638,
    "Store Name": "The Co-operative Funeralcare - Rose Green",
    "Monday Opening Hours": "10:00 - 16:00",
    "Tuesday Opening Hours": "10:00 - 16:00",
    "Wednesday Opening Hours": "10:00 - 16:00",
    "Thursday Opening Hours": "10:00 - 16:00",
    "Friday Opening Hours": "10:00 - 16:00",
    "Area": 2,
    "Area Client Experience Manager": "Stefan Field",
    "Area Client Experience Manager Phone Number": 7706342321,
    "Street": "6 Nyetimber Lane",
    "Address 1": "Rose Green",
    "Town": "Bognor Regis",
    "Postcode": "PO21 3HG",
    "Telephone": "01243 268681",
    "Email": "rosegreenfuneral@southerncoops.co.uk",
    "Latitude": 50.784648,
    "Longitude": -0.716821,
    "Car Park": "Yes",
    "SharePoint": "https://mostlane.sharepoint.com/Mostlane%20Shared%20Documents/Forms/AllItems.aspx?id=%2FMostlane%20Shared%20Documents%2FMostlane%20Construction%2FTSC%20Compliance%2FELS%2F638%20Rose Green",
    "5_Year": "03/06/2026",
    "PAT": "16/01/2026",
    "EM": "16/01/2026",
    "PV": "",
    "EV": "",
    "PUMP": ""
  },
  {
    "Branch Code": 625,
    "Store Name": "The Co-operative Funeralcare - Uckfield",
    "Monday Opening Hours": "10:00 - 16:00",
    "Tuesday Opening Hours": "10:00 - 16:00",
    "Wednesday Opening Hours": "10:00 - 16:00",
    "Thursday Opening Hours": "10:00 - 16:00",
    "Friday Opening Hours": "10:00 - 16:00",
    "Area": 2,
    "Area Client Experience Manager": "Stefan Field",
    "Area Client Experience Manager Phone Number": 7706342321,
    "Street": "65 High Street",
    "Address 1": "",
    "Town": "Uckfield",
    "Postcode": "TN22 1AP",
    "Telephone": "01825 764125",
    "Email": "uckfieldfuneral@southerncoops.co.uk",
    "Latitude": 50.9713133,
    "Longitude": 0.0963178,
    "Car Park": "Yes",
    "SharePoint": "https://mostlane.sharepoint.com/Mostlane%20Shared%20Documents/Forms/AllItems.aspx?id=%2FMostlane%20Shared%20Documents%2FMostlane%20Construction%2FTSC%20Compliance%2FELS%2F625%20Uckfield",
    "5_Year": "30/11/2026",
    "PAT": "28/01/2026",
    "EM": "28/01/2026",
    "PV": "",
    "EV": "",
    "PUMP": ""
  },
  {
    "Branch Code": 753,
    "Store Name": "The Co-operative Funeralcare with Caring Lady - Brighton",
    "Monday Opening Hours": "10:00 - 16:00",
    "Tuesday Opening Hours": "10:00 - 16:00",
    "Wednesday Opening Hours": "10:00 - 16:00",
    "Thursday Opening Hours": "10:00 - 16:00",
    "Friday Opening Hours": "10:00 - 16:00",
    "Area": 2,
    "Area Client Experience Manager": "Stefan Field",
    "Area Client Experience Manager Phone Number": 7706342321,
    "Street": "155 Lewes Road,",
    "Address 1": "",
    "Town": "Brighton, ",
    "Postcode": "BN2 3LG",
    "Telephone": "01273 626326",
    "Email": "brightonfuneral@southerncoops.co.uk",
    "Latitude": 50.8349674,
    "Longitude": -0.1261597,
    "Car Park": "No",
    "SharePoint": "https://mostlane.sharepoint.com/Mostlane%20Shared%20Documents/Forms/AllItems.aspx?id=%2FMostlane%20Shared%20Documents%2FMostlane%20Construction%2FTSC%20Compliance%2FELS%2F753%20CLFD Brighton",
    "5_Year": "12/10/2026",
    "PAT": "13/01/2026",
    "EM": "13/01/2026",
    "PV": "",
    "EV": "",
    "PUMP": ""
  },
  {
    "Branch Code": 756,
    "Store Name": "The Co-operative Funeralcare with Caring Lady - Goring-by-Sea",
    "Monday Opening Hours": "10:00 - 16:00",
    "Tuesday Opening Hours": "10:00 - 16:00",
    "Wednesday Opening Hours": "10:00 - 16:00",
    "Thursday Opening Hours": "10:00 - 16:00",
    "Friday Opening Hours": "10:00 - 16:00",
    "Area": 2,
    "Area Client Experience Manager": "Stefan Field",
    "Area Client Experience Manager Phone Number": 7706342321,
    "Street": "56 Goring Road,  ",
    "Address 1": "Goring by Sea, ",
    "Town": "Worthing,",
    "Postcode": "BN12 4AD",
    "Telephone": "01903 505757",
    "Email": "goringfuneral@southerncoops.co.uk",
    "Latitude": 50.8134729,
    "Longitude": -0.4033163,
    "Car Park": "No",
    "SharePoint": "https://mostlane.sharepoint.com/Mostlane%20Shared%20Documents/Forms/AllItems.aspx?id=%2FMostlane%20Shared%20Documents%2FMostlane%20Construction%2FTSC%20Compliance%2FELS%2F756%20CLFD Goring-by-Sea",
    "5_Year": "05/07/2027",
    "PAT": "15/01/2026",
    "EM": "15/01/2026",
    "PV": "",
    "EV": "",
    "PUMP": ""
  },
  {
    "Branch Code": 752,
    "Store Name": "The Co-operative Funeralcare with Caring Lady - Hove",
    "Monday Opening Hours": "10:00 - 16:00",
    "Tuesday Opening Hours": "10:00 - 16:00",
    "Wednesday Opening Hours": "10:00 - 16:00",
    "Thursday Opening Hours": "10:00 - 16:00",
    "Friday Opening Hours": "10:00 - 16:00",
    "Area": 2,
    "Area Client Experience Manager": "Stefan Field",
    "Area Client Experience Manager Phone Number": 7706342321,
    "Street": "38 Blatchington Road,  ",
    "Address 1": "",
    "Town": "Hove,",
    "Postcode": "BN3 3YH",
    "Telephone": "01273 771332",
    "Email": "hovefuneral@southerncoops.co.uk",
    "Latitude": 50.8314353,
    "Longitude": -0.1755435,
    "Car Park": "No",
    "SharePoint": "https://mostlane.sharepoint.com/Mostlane%20Shared%20Documents/Forms/AllItems.aspx?id=%2FMostlane%20Shared%20Documents%2FMostlane%20Construction%2FTSC%20Compliance%2FELS%2F752%20CLFD Hove",
    "5_Year": "29/11/2026",
    "PAT": "13/01/2026",
    "EM": "13/01/2026",
    "PV": "",
    "EV": "",
    "PUMP": ""
  },
  {
    "Branch Code": 757,
    "Store Name": "The Co-operative Funeralcare with Caring Lady - Peacehaven",
    "Monday Opening Hours": "10:00 - 16:00",
    "Tuesday Opening Hours": "10:00 - 16:00",
    "Wednesday Opening Hours": "10:00 - 16:00",
    "Thursday Opening Hours": "10:00 - 16:00",
    "Friday Opening Hours": "10:00 - 16:00",
    "Area": 2,
    "Area Client Experience Manager": "Stefan Field",
    "Area Client Experience Manager Phone Number": 7706342321,
    "Street": "217 South Coast Road,  ",
    "Address 1": "",
    "Town": "Peacehaven,",
    "Postcode": "BN10 8LA",
    "Telephone": "01273 585818",
    "Email": "peacehavenfuneral@southerncoops.co.uk",
    "Latitude": 50.7910507,
    "Longitude": -0.0006511,
    "Car Park": "No",
    "SharePoint": "https://mostlane.sharepoint.com/Mostlane%20Shared%20Documents/Forms/AllItems.aspx?id=%2FMostlane%20Shared%20Documents%2FMostlane%20Construction%2FTSC%20Compliance%2FELS%2F757%20CLFD Peacehaven",
    "5_Year": "03/10/2025",
    "PAT": "13/02/2026",
    "EM": "13/02/2026",
    "PV": "",
    "EV": "",
    "PUMP": ""
  },
  {
    "Branch Code": 754,
    "Store Name": "The Co-operative Funeralcare with Caring Lady - Shoreham-by-Sea",
    "Monday Opening Hours": "10:00 - 16:00",
    "Tuesday Opening Hours": "10:00 - 16:00",
    "Wednesday Opening Hours": "10:00 - 16:00",
    "Thursday Opening Hours": "10:00 - 16:00",
    "Friday Opening Hours": "10:00 - 16:00",
    "Area": 2,
    "Area Client Experience Manager": "Stefan Field",
    "Area Client Experience Manager Phone Number": 7706342321,
    "Street": "68 High Street, ",
    "Address 1": "",
    "Town": "Shoreham by Sea,",
    "Postcode": "BN43 5DB",
    "Telephone": "01273 464647",
    "Email": "shorehamfuneral@southerncoops.co.uk",
    "Latitude": 50.8323791,
    "Longitude": -0.2775352,
    "Car Park": "No",
    "SharePoint": "https://mostlane.sharepoint.com/Mostlane%20Shared%20Documents/Forms/AllItems.aspx?id=%2FMostlane%20Shared%20Documents%2FMostlane%20Construction%2FTSC%20Compliance%2FELS%2F754%20CLFD Shoreham-by-Sea",
    "5_Year": "07/10/2026",
    "PAT": "13/02/2026",
    "EM": "13/02/2026",
    "PV": "",
    "EV": "",
    "PUMP": ""
  },
  {
    "Branch Code": 685,
    "Store Name": "The Co-operative Funeralcare - East Cowes",
    "Monday Opening Hours": "10:00 - 16:00",
    "Tuesday Opening Hours": "10:00 - 16:00",
    "Wednesday Opening Hours": "10:00 - 16:00",
    "Thursday Opening Hours": "10:00 - 16:00",
    "Friday Opening Hours": "10:00 - 16:00",
    "Area": 3,
    "Area Client Experience Manager": "Alex Morley",
    "Area Client Experience Manager Phone Number": 7885843883,
    "Street": "8-10 Ferry Road",
    "Address 1": "",
    "Town": "East  Cowes",
    "Postcode": "PO32 6RA",
    "Telephone": "01983 291263",
    "Email": "eastcowesfuneral@southerncoops.co.uk",
    "Latitude": 50.7575832,
    "Longitude": -1.2886651,
    "Car Park": "No",
    "SharePoint": "https://mostlane.sharepoint.com/Mostlane%20Shared%20Documents/Forms/AllItems.aspx?id=%2FMostlane%20Shared%20Documents%2FMostlane%20Construction%2FTSC%20Compliance%2FELS%2F685%20East Cowes",
    "5_Year": "25/05/2027",
    "PAT": "03/12/2025",
    "EM": "03/12/2025",
    "PV": "",
    "EV": "",
    "PUMP": ""
  },
  {
    "Branch Code": 659,
    "Store Name": "The Co-operative Funeralcare - Fareham",
    "Monday Opening Hours": "09:00 - 17:00",
    "Tuesday Opening Hours": "09:00 - 17:00",
    "Wednesday Opening Hours": "09:00 - 17:00",
    "Thursday Opening Hours": "09:00 - 17:00",
    "Friday Opening Hours": "09:00 - 17:00",
    "Area": 3,
    "Area Client Experience Manager": "Tracie Sharp",
    "Area Client Experience Manager Phone Number": 7885843887,
    "Street": "86 Trinity Street",
    "Address 1": "",
    "Town": "Fareham",
    "Postcode": "PO16 7SJ",
    "Telephone": "01329 280249",
    "Email": "FarehamFuneral@southerncoops.co.uk",
    "Latitude": 50.8551741,
    "Longitude": -1.1836343,
    "Car Park": "Yes",
    "SharePoint": "https://mostlane.sharepoint.com/Mostlane%20Shared%20Documents/Forms/AllItems.aspx?id=%2FMostlane%20Shared%20Documents%2FMostlane%20Construction%2FTSC%20Compliance%2FELS%2F659%20Fareham",
    "5_Year": "07/12/2026",
    "PAT": "31/01/2026",
    "EM": "31/01/2026",
    "PV": "",
    "EV": "",
    "PUMP": ""
  },
  {
    "Branch Code": 639,
    "Store Name": "The Co-operative Funeralcare - Freshwater",
    "Monday Opening Hours": "10:00 - 16:00",
    "Tuesday Opening Hours": "10:00 - 16:00",
    "Wednesday Opening Hours": "10:00 - 16:00",
    "Thursday Opening Hours": "10:00 - 16:00",
    "Friday Opening Hours": "10:00 - 16:00",
    "Area": 3,
    "Area Client Experience Manager": "Alex Morley",
    "Area Client Experience Manager Phone Number": 7885843883,
    "Street": "The Avenue",
    "Address 1": "",
    "Town": "Freshwater",
    "Postcode": "PO40 9UU",
    "Telephone": "01983 756503",
    "Email": "Freshwaterfuneral@southerncoops.co.uk",
    "Latitude": 50.6838445,
    "Longitude": -1.5289451,
    "Car Park": "Yes",
    "SharePoint": "https://mostlane.sharepoint.com/Mostlane%20Shared%20Documents/Forms/AllItems.aspx?id=%2FMostlane%20Shared%20Documents%2FMostlane%20Construction%2FTSC%20Compliance%2FELS%2F639%20Freshwater",
    "5_Year": "22/12/2026",
    "PAT": "02/12/2025",
    "EM": "02/12/2025",
    "PV": "",
    "EV": "",
    "PUMP": ""
  },
  {
    "Branch Code": 622,
    "Store Name": "The Co-operative Funeralcare - Frome ",
    "Monday Opening Hours": "10:00 - 16:00",
    "Tuesday Opening Hours": "10:00 - 16:00",
    "Wednesday Opening Hours": "10:00 - 16:00",
    "Thursday Opening Hours": "10:00 - 16:00",
    "Friday Opening Hours": "10:00 - 16:00",
    "Area": 3,
    "Area Client Experience Manager": "Alex Morley",
    "Area Client Experience Manager Phone Number": 7885843883,
    "Street": "1 Nunney Road",
    "Address 1": "",
    "Town": "Frome",
    "Postcode": "BA11 4LA",
    "Telephone": "01373 473426",
    "Email": "FromeFuneral@southerncoops.co.uk",
    "Latitude": 51.23069,
    "Longitude": -2.327988,
    "Car Park": "Yes",
    "SharePoint": "https://mostlane.sharepoint.com/Mostlane%20Shared%20Documents/Forms/AllItems.aspx?id=%2FMostlane%20Shared%20Documents%2FMostlane%20Construction%2FTSC%20Compliance%2FELS%2F622%20Frome",
    "5_Year": "02/12/2026",
    "PAT": "09/09/2026",
    "EM": "09/09/2026",
    "PV": "",
    "EV": "",
    "PUMP": ""
  },
  {
    "Branch Code": 687,
    "Store Name": "The Co-operative Funeralcare - Gillingham",
    "Monday Opening Hours": "10:00 - 16:00",
    "Tuesday Opening Hours": "10:00 - 16:00",
    "Wednesday Opening Hours": "10:00 - 16:00",
    "Thursday Opening Hours": "10:00 - 16:00",
    "Friday Opening Hours": "10:00 - 16:00",
    "Area": 3,
    "Area Client Experience Manager": "Alex Morley",
    "Area Client Experience Manager Phone Number": 7885843883,
    "Street": "2 High Street",
    "Address 1": "",
    "Town": "Gillingham",
    "Postcode": "SP8 4QT",
    "Telephone": "01747 824738",
    "Email": "gillinghamfuneral@southerncoops.co.uk",
    "Latitude": 51.0369573,
    "Longitude": -2.2727088,
    "Car Park": "No",
    "SharePoint": "https://mostlane.sharepoint.com/Mostlane%20Shared%20Documents/Forms/AllItems.aspx?id=%2FMostlane%20Shared%20Documents%2FMostlane%20Construction%2FTSC%20Compliance%2FELS%2F687%20Gillingham",
    "5_Year": "03/12/2026",
    "PAT": "26/11/2025",
    "EM": "26/11/2025",
    "PV": "",
    "EV": "",
    "PUMP": ""
  },
  {
    "Branch Code": 652,
    "Store Name": "The Co-operative Funeralcare - Gosport",
    "Monday Opening Hours": "09:00 - 17:00",
    "Tuesday Opening Hours": "09:00 - 17:00",
    "Wednesday Opening Hours": "09:00 - 17:00",
    "Thursday Opening Hours": "09:00 - 17:00",
    "Friday Opening Hours": "09:00 - 17:00",
    "Area": 3,
    "Area Client Experience Manager": "Tracie Sharp",
    "Area Client Experience Manager Phone Number": 7885843887,
    "Street": "147 Stoke Road",
    "Address 1": "",
    "Town": "Gosport",
    "Postcode": "PO12 1SE",
    "Telephone": "02392 581032",
    "Email": "GosportFuneral@southerncoops.co.uk",
    "Latitude": 50.7924199,
    "Longitude": -1.1361257,
    "Car Park": "No",
    "SharePoint": "https://mostlane.sharepoint.com/Mostlane%20Shared%20Documents/Forms/AllItems.aspx?id=%2FMostlane%20Shared%20Documents%2FMostlane%20Construction%2FTSC%20Compliance%2FELS%2F652%20Gosport",
    "5_Year": "03/12/2026",
    "PAT": "06/01/2026",
    "EM": "06/01/2026",
    "PV": "",
    "EV": "",
    "PUMP": ""
  },
  {
    "Branch Code": 681,
    "Store Name": "The Co-operative Funeralcare - Lake",
    "Monday Opening Hours": "10:00 - 16:00",
    "Tuesday Opening Hours": "10:00 - 16:00",
    "Wednesday Opening Hours": "10:00 - 16:00",
    "Thursday Opening Hours": "10:00 - 16:00",
    "Friday Opening Hours": "10:00 - 16:00",
    "Area": 3,
    "Area Client Experience Manager": "Alex Morley",
    "Area Client Experience Manager Phone Number": 7885843883,
    "Street": "1 The Fairway",
    "Address 1": "Lake",
    "Town": "Sandown",
    "Postcode": "PO36 9EE",
    "Telephone": "01983 403832",
    "Email": "lakefuneral@southerncoops.co.uk",
    "Latitude": 50.6504125,
    "Longitude": -1.1662969,
    "Car Park": "Yes",
    "SharePoint": "https://mostlane.sharepoint.com/Mostlane%20Shared%20Documents/Forms/AllItems.aspx?id=%2FMostlane%20Shared%20Documents%2FMostlane%20Construction%2FTSC%20Compliance%2FELS%2F681%20Lake",
    "5_Year": "22/12/2026",
    "PAT": "06/12/2025",
    "EM": "06/12/2025",
    "PV": "",
    "EV": "01/07/2025",
    "PUMP": ""
  },
  {
    "Branch Code": 682,
    "Store Name": "The Co-operative Funeralcare - Newport",
    "Monday Opening Hours": "10:00 - 16:00",
    "Tuesday Opening Hours": "10:00 - 16:00",
    "Wednesday Opening Hours": "10:00 - 16:00",
    "Thursday Opening Hours": "10:00 - 16:00",
    "Friday Opening Hours": "10:00 - 16:00",
    "Area": 3,
    "Area Client Experience Manager": "Alex Morley",
    "Area Client Experience Manager Phone Number": 7885843883,
    "Street": "Cranbourn Rest,",
    "Address 1": "61 Upper St James Street",
    "Town": "Newport",
    "Postcode": "PO30 1LQ",
    "Telephone": "01983 537213",
    "Email": "newportfuneral@southerncoops.co.uk",
    "Latitude": 50.6968303,
    "Longitude": -1.295409,
    "Car Park": "Yes",
    "SharePoint": "https://mostlane.sharepoint.com/Mostlane%20Shared%20Documents/Forms/AllItems.aspx?id=%2FMostlane%20Shared%20Documents%2FMostlane%20Construction%2FTSC%20Compliance%2FELS%2F682%20Newport",
    "5_Year": "16/12/2026",
    "PAT": "04/12/2025",
    "EM": "04/12/2025",
    "PV": "",
    "EV": "",
    "PUMP": "30/05/2025"
  },
  {
    "Branch Code": 675,
    "Store Name": "The Co-operative Funeralcare - Rowner",
    "Monday Opening Hours": "10:00 - 16:00",
    "Tuesday Opening Hours": "10:00 - 16:00",
    "Wednesday Opening Hours": "10:00 - 16:00",
    "Thursday Opening Hours": "10:00 - 16:00",
    "Friday Opening Hours": "10:00 - 16:00",
    "Area": 3,
    "Area Client Experience Manager": "Tracie Sharp",
    "Area Client Experience Manager Phone Number": 7885843887,
    "Street": "11 Rowner Road",
    "Address 1": "Rowner",
    "Town": "Gosport",
    "Postcode": "PO13 9UB",
    "Telephone": "02392 502281",
    "Email": "RownerFuneral@southerncoops.co.uk",
    "Latitude": 50.8118834,
    "Longitude": -1.1691836,
    "Car Park": "No",
    "SharePoint": "https://mostlane.sharepoint.com/Mostlane%20Shared%20Documents/Forms/AllItems.aspx?id=%2FMostlane%20Shared%20Documents%2FMostlane%20Construction%2FTSC%20Compliance%2FELS%2F675%20Rowner",
    "5_Year": "08/12/2026",
    "PAT": "06/01/2026",
    "EM": "06/01/2026",
    "PV": "",
    "EV": "",
    "PUMP": ""
  },
  {
    "Branch Code": 683,
    "Store Name": "The Co-operative Funeralcare - Ryde",
    "Monday Opening Hours": "10:00 - 16:00",
    "Tuesday Opening Hours": "10:00 - 16:00",
    "Wednesday Opening Hours": "10:00 - 16:00",
    "Thursday Opening Hours": "10:00 - 16:00",
    "Friday Opening Hours": "10:00 - 16:00",
    "Area": 3,
    "Area Client Experience Manager": "Alex Morley",
    "Area Client Experience Manager Phone Number": 7885843883,
    "Street": "45 St John's Road",
    "Address 1": "",
    "Town": "Ryde",
    "Postcode": "PO33 2RN",
    "Telephone": "01983 615746",
    "Email": "rydefuneral@southerncoops.co.uk",
    "Latitude": 50.7257002,
    "Longitude": -1.1612071,
    "Car Park": "Yes",
    "SharePoint": "https://mostlane.sharepoint.com/Mostlane%20Shared%20Documents/Forms/AllItems.aspx?id=%2FMostlane%20Shared%20Documents%2FMostlane%20Construction%2FTSC%20Compliance%2FELS%2F683%20Ryde",
    "5_Year": "25/08/2027",
    "PAT": "03/12/2025",
    "EM": "03/12/2025",
    "PV": "",
    "EV": "",
    "PUMP": ""
  },
  {
    "Branch Code": 626,
    "Store Name": "The Co-operative Funeralcare - Shaftesbury",
    "Monday Opening Hours": "10:00 - 16:00",
    "Tuesday Opening Hours": "10:00 - 16:00",
    "Wednesday Opening Hours": "10:00 - 16:00",
    "Thursday Opening Hours": "10:00 - 16:00",
    "Friday Opening Hours": "10:00 - 16:00",
    "Area": 3,
    "Area Client Experience Manager": "Alex Morley",
    "Area Client Experience Manager Phone Number": 7885843883,
    "Street": "Greenacre House",
    "Address 1": "Salisbury Road",
    "Town": "Shaftesbury",
    "Postcode": "SP7 8BS",
    "Telephone": "01747 858968",
    "Email": "ShaftesburyFuneral@southerncoops.co.uk",
    "Latitude": 51.0018101,
    "Longitude": -2.179325,
    "Car Park": "Yes",
    "SharePoint": "https://mostlane.sharepoint.com/Mostlane%20Shared%20Documents/Forms/AllItems.aspx?id=%2FMostlane%20Shared%20Documents%2FMostlane%20Construction%2FTSC%20Compliance%2FELS%2F626%20Shaftesbury",
    "5_Year": "03/12/2026",
    "PAT": "21/02/2026",
    "EM": "21/02/2026",
    "PV": "",
    "EV": "08/09/2026",
    "PUMP": ""
  },
  {
    "Branch Code": 684,
    "Store Name": "The Co-operative Funeralcare - Shanklin",
    "Monday Opening Hours": "10:00 - 16:00",
    "Tuesday Opening Hours": "10:00 - 16:00",
    "Wednesday Opening Hours": "10:00 - 16:00",
    "Thursday Opening Hours": "10:00 - 16:00",
    "Friday Opening Hours": "10:00 - 16:00",
    "Area": 3,
    "Area Client Experience Manager": "Alex Morley",
    "Area Client Experience Manager Phone Number": 7885843883,
    "Street": "76 Regent Street",
    "Address 1": "",
    "Town": "Shanklin",
    "Postcode": "PO37 7AP",
    "Telephone": "01983 861196",
    "Email": "shanklinfuneral@southerncoops.co.uk",
    "Latitude": 50.6321381,
    "Longitude": -1.1787634,
    "Car Park": "Yes",
    "SharePoint": "https://mostlane.sharepoint.com/Mostlane%20Shared%20Documents/Forms/AllItems.aspx?id=%2FMostlane%20Shared%20Documents%2FMostlane%20Construction%2FTSC%20Compliance%2FELS%2F684%20Shanklin",
    "5_Year": "06/12/2026",
    "PAT": "05/12/2025",
    "EM": "05/12/2025",
    "PV": "",
    "EV": "",
    "PUMP": ""
  },
  {
    "Branch Code": 620,
    "Store Name": "The Co-operative Funeralcare - Warminster",
    "Monday Opening Hours": "10:00 - 16:00",
    "Tuesday Opening Hours": "10:00 - 16:00",
    "Wednesday Opening Hours": "10:00 - 16:00",
    "Thursday Opening Hours": "10:00 - 16:00",
    "Friday Opening Hours": "10:00 - 16:00",
    "Area": 3,
    "Area Client Experience Manager": "Alex Morley",
    "Area Client Experience Manager Phone Number": 7885843883,
    "Street": "3 George Street",
    "Address 1": "",
    "Town": "Warminster",
    "Postcode": "BA12 8QA",
    "Telephone": "01985 220105",
    "Email": "warminsterfuneral@southerncoops.co.uk",
    "Latitude": 51.2055505,
    "Longitude": -2.1839191,
    "Car Park": "No",
    "SharePoint": "https://mostlane.sharepoint.com/Mostlane%20Shared%20Documents/Forms/AllItems.aspx?id=%2FMostlane%20Shared%20Documents%2FMostlane%20Construction%2FTSC%20Compliance%2FELS%2F620%20Warminster",
    "5_Year": "02/12/2026",
    "PAT": "10/02/2026",
    "EM": "10/02/2026",
    "PV": "",
    "EV": "",
    "PUMP": ""
  },
  {
    "Branch Code": 717,
    "Store Name": "The Co-operative Funeralcare - Alton",
    "Monday Opening Hours": "10:00 - 16:00",
    "Tuesday Opening Hours": "10:00 - 16:00",
    "Wednesday Opening Hours": "10:00 - 16:00",
    "Thursday Opening Hours": "10:00 - 16:00",
    "Friday Opening Hours": "10:00 - 16:00",
    "Area": 4,
    "Area Client Experience Manager": "Ali Davison",
    "Area Client Experience Manager Phone Number": "07821 655333",
    "Street": "71 High Street",
    "Address 1": "",
    "Town": "Alton",
    "Postcode": "GU34 1AB",
    "Telephone": "01420 85298",
    "Email": "altonfuneral@southerncoops.co.uk",
    "Latitude": 51.1474935,
    "Longitude": -0.9771961,
    "Car Park": "No",
    "SharePoint": "https://mostlane.sharepoint.com/Mostlane%20Shared%20Documents/Forms/AllItems.aspx?id=%2FMostlane%20Shared%20Documents%2FMostlane%20Construction%2FTSC%20Compliance%2FELS%2F717%20Alton",
    "5_Year": "28/03/2029",
    "PAT": "14/08/2026",
    "EM": "14/08/2026",
    "PV": "",
    "EV": "",
    "PUMP": ""
  },
  {
    "Branch Code": 654,
    "Store Name": "The Co-operative Funeralcare - Andover",
    "Monday Opening Hours": "10:00 - 16:00",
    "Tuesday Opening Hours": "10:00 - 16:00",
    "Wednesday Opening Hours": "10:00 - 16:00",
    "Thursday Opening Hours": "10:00 - 16:00",
    "Friday Opening Hours": "10:00 - 16:00",
    "Area": 4,
    "Area Client Experience Manager": "Ali Davison",
    "Area Client Experience Manager Phone Number": "07821 655333",
    "Street": "22 London Street",
    "Address 1": "",
    "Town": "Andover",
    "Postcode": "SP10 2PE",
    "Telephone": "01264 334798",
    "Email": "AndoverFuneral@southerncoops.co.uk",
    "Latitude": 51.2061464,
    "Longitude": -1.4761132,
    "Car Park": "Yes",
    "SharePoint": "https://mostlane.sharepoint.com/Mostlane%20Shared%20Documents/Forms/AllItems.aspx?id=%2FMostlane%20Shared%20Documents%2FMostlane%20Construction%2FTSC%20Compliance%2FELS%2F654%20Andover",
    "5_Year": "30/11/2026",
    "PAT": "30/01/2026",
    "EM": "30/01/2026",
    "PV": "",
    "EV": "",
    "PUMP": ""
  },
  {
    "Branch Code": 648,
    "Store Name": "The Co-operative Funeralcare - Ash Vale",
    "Monday Opening Hours": "10:00 - 16:00",
    "Tuesday Opening Hours": "10:00 - 16:00",
    "Wednesday Opening Hours": "10:00 - 16:00",
    "Thursday Opening Hours": "10:00 - 16:00",
    "Friday Opening Hours": "10:00 - 16:00",
    "Area": 4,
    "Area Client Experience Manager": "Ali Davison",
    "Area Client Experience Manager Phone Number": "07821 655333",
    "Street": "231 Shawfield Road",
    "Address 1": "",
    "Town": "Ash Vale",
    "Postcode": "GU12 5DL",
    "Telephone": "01252 330834",
    "Email": "AshValeFuneral@southerncoops.co.uk",
    "Latitude": 51.2569454,
    "Longitude": -0.7211028,
    "Car Park": "Yes",
    "SharePoint": "https://mostlane.sharepoint.com/Mostlane%20Shared%20Documents/Forms/AllItems.aspx?id=%2FMostlane%20Shared%20Documents%2FMostlane%20Construction%2FTSC%20Compliance%2FELS%2F648%20Ash Vale",
    "5_Year": "25/11/2026",
    "PAT": "24/01/2026",
    "EM": "24/01/2026",
    "PV": "",
    "EV": "",
    "PUMP": ""
  },
  {
    "Branch Code": 615,
    "Store Name": "The Co-operative Funeralcare - Aylesbury",
    "Monday Opening Hours": "10:00 - 16:00",
    "Tuesday Opening Hours": "10:00 - 16:00",
    "Wednesday Opening Hours": "10:00 - 16:00",
    "Thursday Opening Hours": "10:00 - 16:00",
    "Friday Opening Hours": "10:00 - 16:00",
    "Area": 4,
    "Area Client Experience Manager": "Ali Davison",
    "Area Client Experience Manager Phone Number": "07821 655333",
    "Street": "73 Park Street",
    "Address 1": "",
    "Town": "Aylesbury",
    "Postcode": "HP20 1DU",
    "Telephone": "01296 395356",
    "Email": "aylesburyfuneral@southerncoops.co.uk",
    "Latitude": 51.8187812,
    "Longitude": -0.804195,
    "Car Park": "No",
    "SharePoint": "https://mostlane.sharepoint.com/Mostlane%20Shared%20Documents/Forms/AllItems.aspx?id=%2FMostlane%20Shared%20Documents%2FMostlane%20Construction%2FTSC%20Compliance%2FELS%2F615%20Aylesbury",
    "5_Year": "17/08/2027",
    "PAT": "14/02/2026",
    "EM": "14/02/2026",
    "PV": "",
    "EV": "",
    "PUMP": ""
  },
  {
    "Branch Code": 644,
    "Store Name": "The Co-operative Funeralcare - Basingstoke",
    "Monday Opening Hours": "10:00 - 16:00",
    "Tuesday Opening Hours": "10:00 - 16:00",
    "Wednesday Opening Hours": "10:00 - 16:00",
    "Thursday Opening Hours": "10:00 - 16:00",
    "Friday Opening Hours": "10:00 - 16:00",
    "Area": 4,
    "Area Client Experience Manager": "Ali Davison",
    "Area Client Experience Manager Phone Number": "07821 655333",
    "Street": "1 Buckland Parade",
    "Address 1": "Buckland Road",
    "Town": "Basingstoke",
    "Postcode": "RG22 6JW",
    "Telephone": "01256 351606",
    "Email": "BasingstokeFuneral@southerncoops.co.uk",
    "Latitude": 51.2502118,
    "Longitude": -1.1183018,
    "Car Park": "No",
    "SharePoint": "https://mostlane.sharepoint.com/Mostlane%20Shared%20Documents/Forms/AllItems.aspx?id=%2FMostlane%20Shared%20Documents%2FMostlane%20Construction%2FTSC%20Compliance%2FELS%2F644%20Basingstoke",
    "5_Year": "26/10/2026",
    "PAT": "30/01/2026",
    "EM": "30/01/2026",
    "PV": "",
    "EV": "",
    "PUMP": ""
  },
  {
    "Branch Code": 647,
    "Store Name": "The Co-operative Funeralcare - Bracknell",
    "Monday Opening Hours": "10:00 - 16:00",
    "Tuesday Opening Hours": "10:00 - 16:00",
    "Wednesday Opening Hours": "10:00 - 16:00",
    "Thursday Opening Hours": "10:00 - 16:00",
    "Friday Opening Hours": "10:00 - 16:00",
    "Area": 4,
    "Area Client Experience Manager": "Ali Davison",
    "Area Client Experience Manager Phone Number": "07821 655333",
    "Street": "12 Rectory Row",
    "Address 1": "East Hampstead",
    "Town": "Bracknell",
    "Postcode": "RG12 7BN",
    "Telephone": "01344 454398",
    "Email": "BracknellFuneral@southerncoops.co.uk",
    "Latitude": 51.404861,
    "Longitude": -0.7556491,
    "Car Park": "No",
    "SharePoint": "https://mostlane.sharepoint.com/Mostlane%20Shared%20Documents/Forms/AllItems.aspx?id=%2FMostlane%20Shared%20Documents%2FMostlane%20Construction%2FTSC%20Compliance%2FELS%2F647%20Bracknell",
    "5_Year": "24/11/2026",
    "PAT": "04/02/2026",
    "EM": "04/02/2026",
    "PV": "",
    "EV": "",
    "PUMP": ""
  },
  {
    "Branch Code": 657,
    "Store Name": "The Co-operative Funeralcare - Farnborough",
    "Monday Opening Hours": "09:00 - 17:00",
    "Tuesday Opening Hours": "09:00 - 17:00",
    "Wednesday Opening Hours": "09:00 - 17:00",
    "Thursday Opening Hours": "09:00 - 17:00",
    "Friday Opening Hours": "09:00 - 17:00",
    "Area": 4,
    "Area Client Experience Manager": "Ali Davison",
    "Area Client Experience Manager Phone Number": "07821 655333",
    "Street": "68 Victoria Road",
    "Address 1": "",
    "Town": "Farnborough",
    "Postcode": "GU14 7PH",
    "Telephone": "01252 542236",
    "Email": "FarnboroughFuneral@southerncoops.co.uk",
    "Latitude": 51.2932806,
    "Longitude": -0.7586653,
    "Car Park": "Yes",
    "SharePoint": "https://mostlane.sharepoint.com/Mostlane%20Shared%20Documents/Forms/AllItems.aspx?id=%2FMostlane%20Shared%20Documents%2FMostlane%20Construction%2FTSC%20Compliance%2FELS%2F657%20Farnborough",
    "5_Year": "28/10/2026",
    "PAT": "23/01/2026",
    "EM": "23/01/2026",
    "PV": "",
    "EV": "",
    "PUMP": ""
  },
  {
    "Branch Code": 669,
    "Store Name": "The Co-operative Funeralcare - Fleet",
    "Monday Opening Hours": "09:00 - 17:00",
    "Tuesday Opening Hours": "09:00 - 17:00",
    "Wednesday Opening Hours": "09:00 - 17:00",
    "Thursday Opening Hours": "09:00 - 17:00",
    "Friday Opening Hours": "09:00 - 17:00",
    "Area": 4,
    "Area Client Experience Manager": "Ali Davison",
    "Area Client Experience Manager Phone Number": "07821 655333",
    "Street": "287 Fleet Road",
    "Address 1": "",
    "Town": "Fleet",
    "Postcode": "GU51 3BT",
    "Telephone": "01252 623098",
    "Email": "FleetFuneral@southerncoops.co.uk",
    "Latitude": 51.2795462,
    "Longitude": -0.8437851,
    "Car Park": "Yes",
    "SharePoint": "https://mostlane.sharepoint.com/Mostlane%20Shared%20Documents/Forms/AllItems.aspx?id=%2FMostlane%20Shared%20Documents%2FMostlane%20Construction%2FTSC%20Compliance%2FELS%2F669%20Fleet",
    "5_Year": "16/09/2026",
    "PAT": "23/01/2026",
    "EM": "23/01/2026",
    "PV": "",
    "EV": "",
    "PUMP": ""
  },
  {
    "Branch Code": 716,
    "Store Name": "The Co-operative Funeralcare - Frimley Green",
    "Monday Opening Hours": "10:00 - 16:00",
    "Tuesday Opening Hours": "10:00 - 16:00",
    "Wednesday Opening Hours": "10:00 - 16:00",
    "Thursday Opening Hours": "10:00 - 16:00",
    "Friday Opening Hours": "10:00 - 16:00",
    "Area": 4,
    "Area Client Experience Manager": "Ali Davison",
    "Area Client Experience Manager Phone Number": "07821 655333",
    "Street": "3 Wharf Road",
    "Address 1": "Frimley Green",
    "Town": "Camberley",
    "Postcode": "GU16 6LE",
    "Telephone": "01252 837506",
    "Email": "frimleygreenfuneral@southerncoops.co.uk",
    "Latitude": 51.3024995,
    "Longitude": -0.7272542,
    "Car Park": "No",
    "SharePoint": "https://mostlane.sharepoint.com/Mostlane%20Shared%20Documents/Forms/AllItems.aspx?id=%2FMostlane%20Shared%20Documents%2FMostlane%20Construction%2FTSC%20Compliance%2FELS%2F716%20Frimley Green",
    "5_Year": "25/07/2028",
    "PAT": "15/09/2026",
    "EM": "15/09/2026",
    "PV": "",
    "EV": "",
    "PUMP": ""
  },
  {
    "Branch Code": 618,
    "Store Name": "The Co-operative Funeralcare - Hazlemere",
    "Monday Opening Hours": "10:00 - 16:00",
    "Tuesday Opening Hours": "10:00 - 16:00",
    "Wednesday Opening Hours": "10:00 - 16:00",
    "Thursday Opening Hours": "10:00 - 16:00",
    "Friday Opening Hours": "10:00 - 16:00",
    "Area": 4,
    "Area Client Experience Manager": "Ali Davison",
    "Area Client Experience Manager Phone Number": "07821 655333",
    "Street": "21 Park Parade Centre",
    "Address 1": "",
    "Town": "Hazlemere",
    "Postcode": "HP15 7AA",
    "Telephone": "01494 717347",
    "Email": "hazlemerefuneral@southerncoops.co.uk",
    "Latitude": 51.65788,
    "Longitude": -0.7095995,
    "Car Park": "Yes",
    "SharePoint": "https://mostlane.sharepoint.com/Mostlane%20Shared%20Documents/Forms/AllItems.aspx?id=%2FMostlane%20Shared%20Documents%2FMostlane%20Construction%2FTSC%20Compliance%2FELS%2F618%20Hazlemere",
    "5_Year": "21/09/2027",
    "PAT": "20/01/2026",
    "EM": "20/01/2026",
    "PV": "",
    "EV": "",
    "PUMP": ""
  },
  {
    "Branch Code": 617,
    "Store Name": "The Co-operative Funeralcare - High Wycombe",
    "Monday Opening Hours": "10:00 - 16:00",
    "Tuesday Opening Hours": "10:00 - 16:00",
    "Wednesday Opening Hours": "10:00 - 16:00",
    "Thursday Opening Hours": "10:00 - 16:00",
    "Friday Opening Hours": "10:00 - 16:00",
    "Area": 4,
    "Area Client Experience Manager": "Ali Davison",
    "Area Client Experience Manager Phone Number": "07821 655333",
    "Street": "110 Dashwood Avenue",
    "Address 1": "",
    "Town": "High Wycombe",
    "Postcode": "HP12 3EB",
    "Telephone": "01494 451292",
    "Email": "highwycombefuneral@southerncoops.co.uk",
    "Latitude": 51.6337964,
    "Longitude": -0.7727324,
    "Car Park": "No",
    "SharePoint": "https://mostlane.sharepoint.com/Mostlane%20Shared%20Documents/Forms/AllItems.aspx?id=%2FMostlane%20Shared%20Documents%2FMostlane%20Construction%2FTSC%20Compliance%2FELS%2F617%20High Wycombe",
    "5_Year": "20/09/2027",
    "PAT": "20/01/2026",
    "EM": "20/01/2026",
    "PV": "",
    "EV": "",
    "PUMP": ""
  },
  {
    "Branch Code": 674,
    "Store Name": "The Co-operative Funeralcare - Liss",
    "Monday Opening Hours": "10:00 - 16:00",
    "Tuesday Opening Hours": "10:00 - 16:00",
    "Wednesday Opening Hours": "10:00 - 16:00",
    "Thursday Opening Hours": "10:00 - 16:00",
    "Friday Opening Hours": "10:00 - 16:00",
    "Area": 4,
    "Area Client Experience Manager": "Ali Davison",
    "Area Client Experience Manager Phone Number": "07821 655333",
    "Street": "3 Lower Mead",
    "Address 1": "Hillbrow Road",
    "Town": "Liss",
    "Postcode": "GU33 7RL",
    "Telephone": "01730 895593",
    "Email": "LissFuneral@southerncoops.co.uk",
    "Latitude": 51.0427425,
    "Longitude": -0.892212,
    "Car Park": "No",
    "SharePoint": "https://mostlane.sharepoint.com/Mostlane%20Shared%20Documents/Forms/AllItems.aspx?id=%2FMostlane%20Shared%20Documents%2FMostlane%20Construction%2FTSC%20Compliance%2FELS%2F674%20Liss",
    "5_Year": "16/12/2026",
    "PAT": "09/05/2026",
    "EM": "09/05/2026",
    "PV": "",
    "EV": "",
    "PUMP": ""
  },
  {
    "Branch Code": 616,
    "Store Name": "The Co-operative Funeralcare - Wendover",
    "Monday Opening Hours": "10:00 - 16:00",
    "Tuesday Opening Hours": "10:00 - 16:00",
    "Wednesday Opening Hours": "10:00 - 16:00",
    "Thursday Opening Hours": "10:00 - 16:00",
    "Friday Opening Hours": "10:00 - 16:00",
    "Area": 4,
    "Area Client Experience Manager": "Ali Davison",
    "Area Client Experience Manager Phone Number": "07821 655333",
    "Street": "3 Holly Court",
    "Address 1": "Tring Road",
    "Town": "Wendover",
    "Postcode": "HP22 6PE",
    "Telephone": "01296 696224",
    "Email": "wendoverfuneral@southerncoops.co.uk",
    "Latitude": 51.7634789,
    "Longitude": -0.740252,
    "Car Park": "Yes",
    "SharePoint": "https://mostlane.sharepoint.com/Mostlane%20Shared%20Documents/Forms/AllItems.aspx?id=%2FMostlane%20Shared%20Documents%2FMostlane%20Construction%2FTSC%20Compliance%2FELS%2F616%20Wendover",
    "5_Year": "22/09/2027",
    "PAT": "14/02/2026",
    "EM": "14/02/2026",
    "PV": "",
    "EV": "",
    "PUMP": ""
  },
  {
    "Branch Code": 711,
    "Store Name": "The Co-operative Funeralcare - Whitchurch",
    "Monday Opening Hours": "10:00 - 16:00",
    "Tuesday Opening Hours": "10:00 - 16:00",
    "Wednesday Opening Hours": "10:00 - 16:00",
    "Thursday Opening Hours": "10:00 - 16:00",
    "Friday Opening Hours": "10:00 - 16:00",
    "Area": 4,
    "Area Client Experience Manager": "Ali Davison",
    "Area Client Experience Manager Phone Number": "07821 655333",
    "Street": "3 Winchester Street",
    "Address 1": "",
    "Town": "Whitchurch",
    "Postcode": "RG28 7AH",
    "Telephone": "01256 895914",
    "Email": "WhitchurchFuneral@southerncoops.co.uk",
    "Latitude": 51.2299415,
    "Longitude": -1.3396063,
    "Car Park": "No",
    "SharePoint": "https://mostlane.sharepoint.com/Mostlane%20Shared%20Documents/Forms/AllItems.aspx?id=%2FMostlane%20Shared%20Documents%2FMostlane%20Construction%2FTSC%20Compliance%2FELS%2F711%20Whitchurch",
    "5_Year": "26/05/2030",
    "PAT": "09/05/2026",
    "EM": "09/05/2026",
    "PV": "",
    "EV": "",
    "PUMP": ""
  }
]
